hyphen/__init__.py
hyphen/base_client.py
hyphen/feature_toggle.py
hyphen/link.py
hyphen/net_info.py
hyphen/types.py
hyphen-0.5.0.dist-info/licenses/LICENSE
hyphen-0.5.0.dist-info/METADATA
hyphen-0.5.0.dist-info/WHEEL
hyphen-0.5.0.dist-info/top_level.txt
hyphen-0.5.0.dist-info/RECORD
