Metadata-Version: 2.4
Name: hyphen
Version: 0.5.0
Summary: Python SDK for Hyphen - Feature toggles, IP geolocation, and link shortening
Author: Hyphen, Inc.
License: MIT
Project-URL: Homepage, https://github.com/Hyphen/python-sdk
Project-URL: Documentation, https://docs.hyphen.ai
Project-URL: Repository, https://github.com/Hyphen/python-sdk
Keywords: hyphen,feature-flags,feature-toggles,link-shortening,ip-geolocation
Classifier: Development Status :: 3 - Alpha
Classifier: Intended Audience :: Developers
Classifier: License :: OSI Approved :: MIT License
Classifier: Programming Language :: Python :: 3
Classifier: Programming Language :: Python :: 3.10
Classifier: Programming Language :: Python :: 3.11
Classifier: Programming Language :: Python :: 3.12
Classifier: Programming Language :: Python :: 3.13
Requires-Python: >=3.10
License-File: LICENSE
Requires-Dist: requests>=2.31.0
Requires-Dist: typing_extensions>=4.0.0
Provides-Extra: dev
Requires-Dist: pytest>=7.4.0; extra == "dev"
Requires-Dist: pytest-cov>=4.1.0; extra == "dev"
Requires-Dist: pytest-asyncio>=0.21.0; extra == "dev"
Requires-Dist: python-dotenv>=1.0.0; extra == "dev"
Requires-Dist: ruff>=0.1.0; extra == "dev"
Requires-Dist: mypy>=1.5.0; extra == "dev"
Requires-Dist: types-requests>=2.31.0; extra == "dev"
Dynamic: license-file
